amongUsAPI/__init__.py
AmongUsAPI-0.0.1.dist-info/LICENSE
AmongUsAPI-0.0.1.dist-info/METADATA
AmongUsAPI-0.0.1.dist-info/WHEEL
AmongUsAPI-0.0.1.dist-info/top_level.txt
AmongUsAPI-0.0.1.dist-info/RECORD
