Metadata-Version: 2.1
Name: AmongUsAPI
Version: 0.0.1
Summary: For interacting with Among Us
Home-page: https://www.beyonce.com
Author: hunterg
Author-email: redissuslolol@gmail.com
License: UNKNOWN
Platform: UNKNOWN
Classifier: Programming Language :: Python :: 3
Classifier: License :: OSI Approved :: MIT License
Classifier: Operating System :: OS Independent
Requires-Python: >=3.6
Requires-Dist: pyscreenshot
Requires-Dist: pyautogui
Requires-Dist: pywin32
Requires-Dist: more-properties
Requires-Dist: imagehash
